LICENSE
MANIFEST.in
README.rst
setup.py
django_auditor/__init__.py
django_auditor/auditor.py
django_auditor/models.py
django_auditor/urls.py
django_auditor/views.py
django_auditor.egg-info/PKG-INFO
django_auditor.egg-info/SOURCES.txt
django_auditor.egg-info/dependency_links.txt
django_auditor.egg-info/top_level.txt
django_auditor/migrations/__init__.py
django_auditor/templates/auditor/admin.html