Metadata-Version: 1.1
Name: django-auditor
Version: 1.0
Summary: This Django app logs changes of models objects in a simple and granular way.
Home-page: https://github.com/brunobastos/django-auditor
Author: Bruno Bastos
Author-email: zerobruno@gmail.com
License: MIT
Keywords: django log audit
Platform: UNKNOWN
Classifier: Environment :: Web Environment
Classifier: Framework :: Django
Classifier: Framework :: Django :: 1.8
Classifier: Intended Audience :: Developers
Classifier: License :: OSI Approved :: MIT License
Classifier: Operating System :: OS Independent
Classifier: Programming Language :: Python
Classifier: Programming Language :: Python :: 3.4
Classifier: Topic :: Software Development :: Libraries
Classifier: Topic :: System :: Logging
